{
  "nodes_info": {
    "ami-5af77f32": {
      "region": "us-east-1",
      "type": "wheezy",
      "os_type": "debian",
      "display_name": "Wheezy",
      "png": "wheezy.png",
      "sizes": [
        "t1.micro",
        "m1.small",
        "m1.medium"
      ]
    },
    "ami-5cf77f34": {
      "region": "us-east-1",
      "type": "precise",
      "os_type": "ubuntu",
      "display_name": "Precise",
      "png": "precise.png",
      "sizes": [
        "t1.micro",
        "m1.small",
        "m1.medium"
      ]
    },
    "ami-5ef77f36": {
      "region": "us-east-1",
      "type": "rhel6",
      "os_type": "redhat",
      "display_name": "Rhel6",
      "png": "rhel6.png",
      "sizes": [
        "t1.micro",
        "m1.small",
        "m1.medium"
      ]
    },
    "ami-a0f67ec8": {
      "region": "us-east-1",
      "type": "trusty",
      "os_type": "ubuntu",
      "display_name": "Trusty",
      "png": "trusty.png",
      "sizes": [
        "t1.micro",
        "m1.small",
        "m1.medium"
      ]
    },
    "ami-5b5b4d1e": {
      "region": "us-west-1",
      "type": "trusty",
      "os_type": "ubuntu",
      "display_name": "Trusty",
      "png": "trusty.png",
      "sizes": [
        "t1.micro",
        "m1.small",
        "m1.medium"
      ]
    },
    "ami-715b4d34": {
      "region": "us-west-1",
      "type": "rhel6",
      "os_type": "redhat",
      "display_name": "Rhel6",
      "png": "rhel6.png",
      "sizes": [
        "t1.micro",
        "m1.small",
        "m1.medium"
      ]
    },
    "ami-735b4d36": {
      "region": "us-west-1",
      "type": "precise",
      "os_type": "ubuntu",
      "display_name": "Precise",
      "png": "precise.png",
      "sizes": [
        "t1.micro",
        "m1.small",
        "m1.medium"
      ]
    },
    "ami-755b4d30": {
      "region": "us-west-1",
      "type": "wheezy",
      "os_type": "debian",
      "display_name": "Wheezy",
      "png": "wheezy.png",
      "sizes": [
        "t1.micro",
        "m1.small",
        "m1.medium"
      ]
    },
    "ami-21165d11": {
      "region": "us-west-2",
      "type": "wheezy",
      "os_type": "debian",
      "display_name": "Wheezy",
      "png": "wheezy.png",
      "sizes": [
        "t1.micro",
        "m1.small",
        "m1.medium"
      ]
    },
    "ami-23165d13": {
      "region": "us-west-2",
      "type": "rhel6",
      "os_type": "redhat",
      "display_name": "Rhel6",
      "png": "rhel6.png",
      "sizes": [
        "t1.micro",
        "m1.small",
        "m1.medium"
      ]
    },
    "ami-25165d15": {
      "region": "us-west-2",
      "type": "precise",
      "os_type": "ubuntu",
      "display_name": "Precise",
      "png": "precise.png",
      "sizes": [
        "t1.micro",
        "m1.small",
        "m1.medium"
      ]
    },
    "ami-db175ceb": {
      "region": "us-west-2",
      "type": "trusty",
      "os_type": "ubuntu",
      "display_name": "Trusty",
      "png": "trusty.png",
      "sizes": [
        "t1.micro",
        "m1.small",
        "m1.medium"
      ]
    },
    "ami-4a8c393d": {
      "region": "eu-west-1",
      "type": "precise",
      "os_type": "ubuntu",
      "display_name": "Precise",
      "png": "precise.png",
      "sizes": [
        "t1.micro",
        "m1.small",
        "m1.medium"
      ]
    },
    "ami-4c8c393b": {
      "region": "eu-west-1",
      "type": "rhel6",
      "os_type": "redhat",
      "display_name": "Rhel6",
      "png": "rhel6.png",
      "sizes": [
        "t1.micro",
        "m1.small",
        "m1.medium"
      ]
    },
    "ami-4e8c3939": {
      "region": "eu-west-1",
      "type": "wheezy",
      "os_type": "debian",
      "display_name": "Wheezy",
      "png": "wheezy.png",
      "sizes": [
        "t1.micro",
        "m1.small",
        "m1.medium"
      ]
    },
    "ami-5c8c392b": {
      "region": "eu-west-1",
      "type": "trusty",
      "os_type": "ubuntu",
      "display_name": "Trusty",
      "png": "trusty.png",
      "sizes": [
        "t1.micro",
        "m1.small",
        "m1.medium"
      ]
    },
    "ami-c6153694": {
      "region": "ap-southeast-1",
      "type": "trusty",
      "os_type": "ubuntu",
      "display_name": "Trusty",
      "png": "trusty.png",
      "sizes": [
        "t1.micro",
        "m1.small",
        "m1.medium"
      ]
    },
    "ami-c815369a": {
      "region": "ap-southeast-1",
      "type": "wheezy",
      "os_type": "debian",
      "display_name": "Wheezy",
      "png": "wheezy.png",
      "sizes": [
        "t1.micro",
        "m1.small",
        "m1.medium"
      ]
    },
    "ami-cc15369e": {
      "region": "ap-southeast-1",
      "type": "rhel6",
      "os_type": "redhat",
      "display_name": "Rhel6",
      "png": "rhel6.png",
      "sizes": [
        "t1.micro",
        "m1.small",
        "m1.medium"
      ]
    },
    "ami-f21536a0": {
      "region": "ap-southeast-1",
      "type": "precise",
      "os_type": "ubuntu",
      "display_name": "Precise",
      "png": "precise.png",
      "sizes": [
        "t1.micro",
        "m1.small",
        "m1.medium"
      ]
    },
    "ami-81aac5bb": {
      "region": "ap-southeast-2",
      "type": "precise",
      "os_type": "ubuntu",
      "display_name": "Precise",
      "png": "precise.png",
      "sizes": [
        "t1.micro",
        "m1.small",
        "m1.medium"
      ]
    },
    "ami-83aac5b9": {
      "region": "ap-southeast-2",
      "type": "rhel6",
      "os_type": "redhat",
      "display_name": "Rhel6",
      "png": "rhel6.png",
      "sizes": [
        "t1.micro",
        "m1.small",
        "m1.medium"
      ]
    },
    "ami-8daac5b7": {
      "region": "ap-southeast-2",
      "type": "wheezy",
      "os_type": "debian",
      "display_name": "Wheezy",
      "png": "wheezy.png",
      "sizes": [
        "t1.micro",
        "m1.small",
        "m1.medium"
      ]
    },
    "ami-97aac5ad": {
      "region": "ap-southeast-2",
      "type": "trusty",
      "os_type": "ubuntu",
      "display_name": "Trusty",
      "png": "trusty.png",
      "sizes": [
        "t1.micro",
        "m1.small",
        "m1.medium"
      ]
    },
    "ami-09a29c08": {
      "region": "ap-northeast-1",
      "type": "wheezy",
      "os_type": "debian",
      "display_name": "Wheezy",
      "png": "wheezy.png",
      "sizes": [
        "t1.micro",
        "m1.small",
        "m1.medium"
      ]
    },
    "ami-45a29c44": {
      "region": "ap-northeast-1",
      "type": "rhel6",
      "os_type": "redhat",
      "display_name": "Rhel6",
      "png": "rhel6.png",
      "sizes": [
        "t1.micro",
        "m1.small",
        "m1.medium"
      ]
    },
    "ami-4ba29c4a": {
      "region": "ap-northeast-1",
      "type": "precise",
      "os_type": "ubuntu",
      "display_name": "Precise",
      "png": "precise.png",
      "sizes": [
        "t1.micro",
        "m1.small",
        "m1.medium"
      ]
    },
    "ami-ada59bac": {
      "region": "ap-northeast-1",
      "type": "trusty",
      "os_type": "ubuntu",
      "display_name": "Trusty",
      "png": "trusty.png",
      "sizes": [
        "t1.micro",
        "m1.small",
        "m1.medium"
      ]
    },
    "ami-21dd6b3c": {
      "region": "sa-east-1",
      "type": "trusty",
      "os_type": "ubuntu",
      "display_name": "Trusty",
      "png": "trusty.png",
      "sizes": [
        "t1.micro",
        "m1.small",
        "m1.medium"
      ]
    },
    "ami-55dd6b48": {
      "region": "sa-east-1",
      "type": "precise",
      "os_type": "ubuntu",
      "display_name": "Precise",
      "png": "precise.png",
      "sizes": [
        "t1.micro",
        "m1.small",
        "m1.medium"
      ]
    },
    "ami-59dd6b44": {
      "region": "sa-east-1",
      "type": "wheezy",
      "os_type": "debian",
      "display_name": "Wheezy",
      "png": "wheezy.png",
      "sizes": [
        "t1.micro",
        "m1.small",
        "m1.medium"
      ]
    },
    "ami-5bdd6b46": {
      "region": "sa-east-1",
      "type": "rhel6",
      "os_type": "redhat",
      "display_name": "Rhel6",
      "png": "rhel6.png",
      "sizes": [
        "t1.micro",
        "m1.small",
        "m1.medium"
      ]
    }
  }
}