{
  "nodes_info": {
    "ami-180a5670": {
      "region": "us-east-1",
      "type": "precise",
      "os_type": "ubuntu",
      "display_name": "Precise",
      "png": "precise.png",
      "sizes": [
        "t1.micro",
        "m1.small",
        "m1.medium"
      ]
    },
    "ami-320a565a": {
      "region": "us-east-1",
      "type": "trusty",
      "os_type": "ubuntu",
      "display_name": "Trusty",
      "png": "trusty.png",
      "sizes": [
        "t1.micro",
        "m1.small",
        "m1.medium"
      ]
    },
    "ami-340a565c": {
      "region": "us-east-1",
      "type": "wheezy",
      "os_type": "debian",
      "display_name": "Wheezy",
      "png": "wheezy.png",
      "sizes": [
        "t1.micro",
        "m1.small",
        "m1.medium"
      ]
    },
    "ami-aa0a56c2": {
      "region": "us-east-1",
      "type": "rhel6",
      "os_type": "redhat",
      "display_name": "Rhel6",
      "png": "rhel6.png",
      "sizes": [
        "t1.micro",
        "m1.small",
        "m1.medium"
      ]
    },
    "ami-9944a1dd": {
      "region": "us-west-1",
      "type": "wheezy",
      "os_type": "debian",
      "display_name": "Wheezy",
      "png": "wheezy.png",
      "sizes": [
        "t1.micro",
        "m1.small",
        "m1.medium"
      ]
    },
    "ami-9f44a1db": {
      "region": "us-west-1",
      "type": "trusty",
      "os_type": "ubuntu",
      "display_name": "Trusty",
      "png": "trusty.png",
      "sizes": [
        "t1.micro",
        "m1.small",
        "m1.medium"
      ]
    },
    "ami-a544a1e1": {
      "region": "us-west-1",
      "type": "precise",
      "os_type": "ubuntu",
      "display_name": "Precise",
      "png": "precise.png",
      "sizes": [
        "t1.micro",
        "m1.small",
        "m1.medium"
      ]
    },
    "ami-af44a1eb": {
      "region": "us-west-1",
      "type": "rhel6",
      "os_type": "redhat",
      "display_name": "Rhel6",
      "png": "rhel6.png",
      "sizes": [
        "t1.micro",
        "m1.small",
        "m1.medium"
      ]
    },
    "ami-03b89933": {
      "region": "us-west-2",
      "type": "trusty",
      "os_type": "ubuntu",
      "display_name": "Trusty",
      "png": "trusty.png",
      "sizes": [
        "t1.micro",
        "m1.small",
        "m1.medium"
      ]
    },
    "ami-05b89935": {
      "region": "us-west-2",
      "type": "wheezy",
      "os_type": "debian",
      "display_name": "Wheezy",
      "png": "wheezy.png",
      "sizes": [
        "t1.micro",
        "m1.small",
        "m1.medium"
      ]
    },
    "ami-6db8995d": {
      "region": "us-west-2",
      "type": "rhel6",
      "os_type": "redhat",
      "display_name": "Rhel6",
      "png": "rhel6.png",
      "sizes": [
        "t1.micro",
        "m1.small",
        "m1.medium"
      ]
    },
    "ami-73b89943": {
      "region": "us-west-2",
      "type": "precise",
      "os_type": "ubuntu",
      "display_name": "Precise",
      "png": "precise.png",
      "sizes": [
        "t1.micro",
        "m1.small",
        "m1.medium"
      ]
    },
    "ami-616ef816": {
      "region": "eu-west-1",
      "type": "rhel6",
      "os_type": "redhat",
      "display_name": "Rhel6",
      "png": "rhel6.png",
      "sizes": [
        "t1.micro",
        "m1.small",
        "m1.medium"
      ]
    },
    "ami-b561f7c2": {
      "region": "eu-west-1",
      "type": "precise",
      "os_type": "ubuntu",
      "display_name": "Precise",
      "png": "precise.png",
      "sizes": [
        "t1.micro",
        "m1.small",
        "m1.medium"
      ]
    },
    "ami-d961f7ae": {
      "region": "eu-west-1",
      "type": "wheezy",
      "os_type": "debian",
      "display_name": "Wheezy",
      "png": "wheezy.png",
      "sizes": [
        "t1.micro",
        "m1.small",
        "m1.medium"
      ]
    },
    "ami-db61f7ac": {
      "region": "eu-west-1",
      "type": "trusty",
      "os_type": "ubuntu",
      "display_name": "Trusty",
      "png": "trusty.png",
      "sizes": [
        "t1.micro",
        "m1.small",
        "m1.medium"
      ]
    }
  }
}
